Metadata-Version: 2.1
Name: appini
Version: 0.0.2
Summary: A tool to create mobile apps from websites using flutter and dart.
Home-page: https://appini.ml/cli
Author: Umut YILDIRIM
Author-email: umut374@gmail.com
License: GNU
Project-URL: Bug Tracker, https://gitlab.com/HopeSweaty/appini/issues
Project-URL: Documentation, https://docs.appini.ml/CLI/get_started/
Project-URL: Source Code, https://gitlab.com/HopeSweaty/appini/
Keywords: mobileapp websites appini
Platform: UNKNOWN
Classifier: Development Status :: 2 - Pre-Alpha
Classifier: Topic :: Utilities
Classifier: License :: OSI Approved :: GNU Lesser General Public License v3 (LGPLv3)
